{
    "network_node_evcard": [
        {
            "address": "云南省昆明市盘龙区龙华路与昙晓路交汇",
            "n_car": "6",
            "Latitude": "25.058888",
            "MID": "4488",
            "Longitude": "102.746111",
            "UID": "3798",
            "name": "中企·万派中心"
        },
        {
            "address": "昆明市盘龙区青云街道龙华路",
            "n_car": "4",
            "Latitude": "25.0677",
            "MID": "5147",
            "Longitude": "102.73888",
            "UID": "3799",
            "name": "中航玺樾"
        },
        {
            "address": "云南省昆明市盘龙区",
            "n_car": "0",
            "Latitude": "25.05805",
            "MID": "5554",
            "Longitude": "102.74555",
            "UID": "3800",
            "name": "昆明测试点"
        },
        {
            "address": "经济技术开发区经邮路与昌宏路交叉口直行300米2号中凰酒店3号门",
            "n_car": "3",
            "Latitude": "25.000789",
            "MID": "5696",
            "Longitude": "102.776519",
            "UID": "3801",
            "name": "中凰酒店"
        },
        {
            "address": "云南省昆明市官渡区玉缘路尽头与博望路交叉路口左侧直行400米后右侧即到",
            "n_car": "6",
            "Latitude": "24.968251",
            "MID": "5770",
            "Longitude": "102.804924",
            "UID": "3802",
            "name": "云南欧通技术"
        },
        {
            "address": "云南省昆明市西山区二环南路678-639号凯旋利汽车市场西场1号场3幢303号",
            "n_car": "6",
            "Latitude": "24.97724",
            "MID": "5967",
            "Longitude": "102.718273",
            "UID": "3803",
            "name": "凯旋利.车博汇"
        }
    ]
}